MANIFEST.in
README.md
setup.py
aostats.egg-info/PKG-INFO
aostats.egg-info/SOURCES.txt
aostats.egg-info/dependency_links.txt
aostats.egg-info/entry_points.txt
aostats.egg-info/requires.txt
aostats.egg-info/top_level.txt
src/__init__.py
src/__main__.py
src/backend_proxy.py
src/engine.py
src/environment.py
src/event_receiver.py
src/version.py
src/assets/about.png
src/assets/albion-stats-icon.png
src/assets/close.png
src/assets/copy.png
src/assets/reset.png
src/consts/__init__.py
src/consts/events.py
src/gui/__init__.py
src/gui/app.py
src/gui/styling.py
src/gui/modules/__init__.py
src/gui/modules/about.py
src/gui/modules/main.py
src/gui/modules/view_type.py
src/gui/modules/views/__init__.py
src/gui/modules/views/copy_button.py
src/gui/modules/views/mode_based_list_view.py
src/gui/modules/views/motd.py
src/gui/modules/views/player_stats.py
src/gui/modules/views/reset_button.py
src/gui/modules/views/stats_type.py
src/gui/modules/views/list_view/__init__.py
src/gui/modules/views/list_view/icon.py
src/gui/modules/views/list_view/list.py
src/stats/__init__.py
src/stats/combat_state.py
src/stats/combat_stats.py
src/stats/fame_stats.py
src/stats/list_item.py
src/stats/statistics.py
src/stats/time_stats.py
src/stats/time_utils.py
src/stats/visibility.py
src/utils/__init__.py
src/utils/assets.py
src/utils/async_request.py
src/utils/config.py
src/utils/names.py
src/utils/number.py
src/utils/version.py
src/utils/weapon.py