Metadata-Version: 2.1
Name: aostats
Version: 1.0.4
Summary: UNKNOWN
Home-page: https://github.com/mazurwiktor/albion-online-stats
Author: Wiktor Mazur
Author-email: wiktormazur1@gmail.com
License: UNKNOWN
Platform: UNKNOWN
